clokta-4.1.3-py3.7-nspkg.pth
clokta/aws_cred_generator.py
clokta/awsrole.py
clokta/clokta_configuration.py
clokta/cloktacli.py
clokta/common.py
clokta/config_parameter.py
clokta/factor_chooser.py
clokta/factors.py
clokta/okta_initiator.py
clokta/role_assumer.py
clokta/role_chooser.py
clokta-4.1.3.dist-info/LICENSE.txt
clokta-4.1.3.dist-info/METADATA
clokta-4.1.3.dist-info/WHEEL
clokta-4.1.3.dist-info/entry_points.txt
clokta-4.1.3.dist-info/namespace_packages.txt
clokta-4.1.3.dist-info/top_level.txt
clokta-4.1.3.dist-info/RECORD
